odoo/addons/l10n_th_fonts/README.rst
odoo/addons/l10n_th_fonts/__init__.py
odoo/addons/l10n_th_fonts/__manifest__.py
odoo/addons/l10n_th_fonts/i18n/l10n_th_fonts.pot
odoo/addons/l10n_th_fonts/models/__init__.py
odoo/addons/l10n_th_fonts/models/res_company.py
odoo/addons/l10n_th_fonts/readme/CONFIGURE.rst
odoo/addons/l10n_th_fonts/readme/CONTRIBUTORS.rst
odoo/addons/l10n_th_fonts/readme/DESCRIPTION.rst
odoo/addons/l10n_th_fonts/static/description/icon.png
odoo/addons/l10n_th_fonts/static/description/index.html
odoo/addons/l10n_th_fonts/static/fonts/AngsanaNew.ttf
odoo/addons/l10n_th_fonts/static/fonts/THSarabunNew.ttf
odoo/addons/l10n_th_fonts/static/scss/fonts_style.scss
odoo/addons/l10n_th_fonts/views/report_templates.xml
odoo13_addon_l10n_th_fonts-13.0.1.0.1.dev4.dist-info/METADATA
odoo13_addon_l10n_th_fonts-13.0.1.0.1.dev4.dist-info/WHEEL
odoo13_addon_l10n_th_fonts-13.0.1.0.1.dev4.dist-info/top_level.txt
odoo13_addon_l10n_th_fonts-13.0.1.0.1.dev4.dist-info/RECORD
